{
  "$schema": "../../../../permissionsSchema.json",
  "permissions": {
    "IdentityRiskEvent.Read.All": {
      "schemes": {
        "DelegatedWork": {
          "type": "DelegatedWork",
          "admin": true,
          "description": "Allows the app to read identity risk event information for all users in your organization on behalf of the signed-in user.",
          "longDescription": "Read identity risk event information"
        },
        "Application": {
          "type": "DelegatedWork",
          "admin": true,
          "description": "Allows the app to read identity risk event information for all users in your organization without a signed-in user.",
          "longDescription": "Read identity risk event information"
        }
      },
      "pathSets": [
        {
          "schemes": [
            "Application",
            "DelegatedWork"
          ],
          "methods": [
            "GET"
          ],
          "paths": {
            "/anonymousipriskevents": {},
            "/anonymousipriskevents/{id}": {},
            "/identityprotection/riskdetections": {},
            "/identityprotection/riskdetections/{id}": {},
            "/identityriskevents": {},
            "/identityriskevents/{id}": {},
            "/impossibletravelriskevents": {},
            "/impossibletravelriskevents/{id}": {},
            "/leakedcredentialsriskevents": {},
            "/leakedcredentialsriskevents/{id}": {},
            "/locatedriskevents/{id}": {},
            "/malwareriskevents": {},
            "/malwareriskevents/{id}": {},
            "/riskdetections": {},
            "/riskdetections/{id}": {},
            "/suspiciousipriskevents": {},
            "/suspiciousipriskevents/{id}": {},
            "/unfamiliarlocationriskevents": {},
            "/unfamiliarlocationriskevents/{id}": {}
          }
        }
      ]
    }
  }
}